wiizin_plots/__init__.py
wiizin_plots/wiizin_plot.py
wiizin_plots-0.0.2.1.dist-info/METADATA
wiizin_plots-0.0.2.1.dist-info/WHEEL
wiizin_plots-0.0.2.1.dist-info/top_level.txt
wiizin_plots-0.0.2.1.dist-info/RECORD
