Metadata-Version: 2.1
Name: wiizin-plots
Version: 0.0.2.1
Summary: Fast EDA plots
Home-page: UNKNOWN
Author: Wiizin
Author-email: <carugaxdopw@hotmail.com>
License: UNKNOWN
Keywords: python,eda,plots
Platform: UNKNOWN
Classifier: Development Status :: 1 - Planning
Classifier: Intended Audience :: Developers
Classifier: Programming Language :: Python :: 3
Classifier: Operating System :: Unix
Classifier: Operating System :: MacOS :: MacOS X
Classifier: Operating System :: Microsoft :: Windows
Requires-Dist: pandas
Requires-Dist: numpy
Requires-Dist: matplotlib
Requires-Dist: seaborn
